console_widgets/__init__.py
console_widgets/console_widgets.py
console_widgets/errors.py
console_widgets/themes.py
console_widgets-0.0.603.dist-info/LICENCE
console_widgets-0.0.603.dist-info/METADATA
console_widgets-0.0.603.dist-info/WHEEL
console_widgets-0.0.603.dist-info/top_level.txt
console_widgets-0.0.603.dist-info/RECORD
