Metadata-Version: 2.1
Name: console-widgets
Version: 0.0.603
Summary: A Python package for displaying terminal based widgets.
Home-page: https://github.com/bornagojsic/console-widgets
Author: Borna Gojšić
Author-email: bornagojsic@gmail.com
License: UNKNOWN
Project-URL: Bug Tracker, https://github.com/bornagojsic/console-widgets/issues
Platform: UNKNOWN
Classifier: Programming Language :: Python :: 3
Classifier: License :: OSI Approved :: MIT License
Classifier: Operating System :: OS Independent
Requires-Python: >=3.6
